niquests/__init__.py
niquests/__version__.py
niquests/_async.py
niquests/_compat.py
niquests/_constant.py
niquests/_typing.py
niquests/adapters.py
niquests/api.py
niquests/async_api.py
niquests/async_session.py
niquests/auth.py
niquests/cookies.py
niquests/exceptions.py
niquests/help.py
niquests/hooks.py
niquests/models.py
niquests/packages.py
niquests/py.typed
niquests/sessions.py
niquests/status_codes.py
niquests/structures.py
niquests/utils.py
niquests/_vendor/__init__.py
niquests/_vendor/kiss_headers/LICENSE
niquests/_vendor/kiss_headers/__init__.py
niquests/_vendor/kiss_headers/api.py
niquests/_vendor/kiss_headers/builder.py
niquests/_vendor/kiss_headers/models.py
niquests/_vendor/kiss_headers/py.typed
niquests/_vendor/kiss_headers/serializer.py
niquests/_vendor/kiss_headers/structures.py
niquests/_vendor/kiss_headers/utils.py
niquests/_vendor/kiss_headers/version.py
niquests/extensions/__init__.py
niquests/extensions/revocation/__init__.py
niquests/extensions/revocation/_crl/__init__.py
niquests/extensions/revocation/_crl/_async/__init__.py
niquests/extensions/revocation/_ocsp/__init__.py
niquests/extensions/revocation/_ocsp/_async/__init__.py
niquests-3.15.1.dist-info/METADATA
niquests-3.15.1.dist-info/WHEEL
niquests-3.15.1.dist-info/licenses/LICENSE
niquests-3.15.1.dist-info/RECORD
