Metadata-Version: 2.4
Name: niquests
Version: 3.15.1
Summary: Niquests is a simple, yet elegant, HTTP library. It is a drop-in replacement for Requests, which is under feature freeze.
Project-URL: Changelog, https://github.com/jawah/niquests/blob/main/HISTORY.md
Project-URL: Documentation, https://niquests.readthedocs.io
Project-URL: Code, https://github.com/jawah/niquests
Project-URL: Issue tracker, https://github.com/jawah/niquests/issues
Author-email: Kenneth Reitz <me@kennethreitz.org>
Maintainer-email: "Ahmed R. TAHRI" <tahri.ahmed@proton.me>
License-Expression: Apache-2.0
License-File: LICENSE
Keywords: QUIC,crl,dns-over-https,dns-over-quic,dns-over-tls,dnssec,doh,doq,dot,http,http client,http/1.1,http2,http3,https,multiplexed,ocsp,requests,revocation,sse,tls,websocket
Classifier: Development Status :: 5 - Production/Stable
Classifier: Environment :: Web Environment
Classifier: Intended Audience :: Developers
Classifier: License :: OSI Approved :: Apache Software License
Classifier: Natural Language :: English
Classifier: Operating System :: OS Independent
Classifier: Programming Language :: Python
Classifier: Programming Language :: Python :: 3
Classifier: Programming Language :: Python :: 3 :: Only
Classifier: Programming Language :: Python :: 3.7
Classifier: Programming Language :: Python :: 3.8
Classifier: Programming Language :: Python :: 3.9
Classifier: Programming Language :: Python :: 3.10
Classifier: Programming Language :: Python :: 3.11
Classifier: Programming Language :: Python :: 3.12
Classifier: Programming Language :: Python :: 3.13
Classifier: Programming Language :: Python :: 3.14
Classifier: Programming Language :: Python :: Implementation :: CPython
Classifier: Programming Language :: Python :: Implementation :: PyPy
Classifier: Topic :: Internet :: WWW/HTTP
Classifier: Topic :: Software Development :: Libraries
Requires-Python: >=3.7
Requires-Dist: charset-normalizer<4,>=2
Requires-Dist: urllib3-future<3,>=2.13.903
Requires-Dist: wassima<3,>=1.0.1
Provides-Extra: brotli
Requires-Dist: urllib3-future[brotli]; extra == 'brotli'
Provides-Extra: full
Requires-Dist: orjson<4,>=3; extra == 'full'
Requires-Dist: urllib3-future[brotli,socks,ws,zstd]; extra == 'full'
Provides-Extra: http3
Requires-Dist: urllib3-future[qh3]; extra == 'http3'
Provides-Extra: ocsp
Requires-Dist: urllib3-future[qh3]; extra == 'ocsp'
Provides-Extra: socks
Requires-Dist: urllib3-future[socks]; extra == 'socks'
Provides-Extra: speedups
Requires-Dist: orjson<4,>=3; extra == 'speedups'
Requires-Dist: urllib3-future[brotli,zstd]; extra == 'speedups'
Provides-Extra: ws
Requires-Dist: urllib3-future[ws]; extra == 'ws'
Provides-Extra: zstd
Requires-Dist: urllib3-future[zstd]; extra == 'zstd'
